pybiocfilecache/__init__.py
pybiocfilecache/cache.py
pybiocfilecache/config.py
pybiocfilecache/const.py
pybiocfilecache/models.py
pybiocfilecache/utils.py
pybiocfilecache-0.7.0.dist-info/licenses/AUTHORS.md
pybiocfilecache-0.7.0.dist-info/licenses/LICENSE.txt
pybiocfilecache-0.7.0.dist-info/METADATA
pybiocfilecache-0.7.0.dist-info/WHEEL
pybiocfilecache-0.7.0.dist-info/top_level.txt
pybiocfilecache-0.7.0.dist-info/RECORD
