Metadata-Version: 2.4
Name: pyBiocFileCache
Version: 0.7.0
Summary: File based cache for resources and metadata
Home-page: https://github.com/biocpy/pyBiocFileCache
Author: jkanche
Author-email: jayaram.kancherla@gmail.com
License: MIT
Project-URL: Documentation, https://github.com/biocpy/pyBiocFileCache
Platform: any
Classifier: Development Status :: 4 - Beta
Classifier: Programming Language :: Python
Requires-Python: >=3.9
License-File: LICENSE.txt
License-File: AUTHORS.md
Requires-Dist: importlib-metadata; python_version < "3.8"
Requires-Dist: sqlalchemy
Requires-Dist: biocframe
Provides-Extra: testing
Requires-Dist: setuptools; extra == "testing"
Requires-Dist: pytest; extra == "testing"
Requires-Dist: pytest-cov; extra == "testing"
Dynamic: license-file
